{
  "instance": "medium",
  "task_count": 20,
  "vehicle_count": 3,
  "sortie_limit": 17,
  "subset_max_size": 6,
  "root_cg_iterations": [
    {
      "iteration": 1,
      "phase": "phase1",
      "rmp_objective": 0.0,
      "artificial_sum": 0.0,
      "route_pool_size": 26
    },
    {
      "iteration": 2,
      "phase": "phase2",
      "rmp_objective": 496.984869,
      "artificial_sum": 0.0,
      "route_pool_size": 26,
      "best_reduced_cost": -77.272711,
      "negative_routes": 4010,
      "added_routes": 200,
      "exhausted": true,
      "label_pops": 13767,
      "generated_labels": 13764
    },
    {
      "iteration": 3,
      "phase": "phase2",
      "rmp_objective": 496.984869,
      "artificial_sum": 0.0,
      "route_pool_size": 226,
      "best_reduced_cost": -52.4358845,
      "negative_routes": 2095,
      "added_routes": 200,
      "exhausted": true,
      "label_pops": 13767,
      "generated_labels": 13764
    },
    {
      "iteration": 4,
      "phase": "phase2",
      "rmp_objective": 496.984869,
      "artificial_sum": 0.0,
      "route_pool_size": 426,
      "best_reduced_cost": -38.884960083,
      "negative_routes": 532,
      "added_routes": 200,
      "exhausted": true,
      "label_pops": 13767,
      "generated_labels": 13764
    },
    {
      "iteration": 5,
      "phase": "phase2",
      "rmp_objective": 496.984869,
      "artificial_sum": 0.0,
      "route_pool_size": 626,
      "best_reduced_cost": -20.887309033,
      "negative_routes": 78,
      "added_routes": 78,
      "exhausted": true,
      "label_pops": 13767,
      "generated_labels": 13764
    },
    {
      "iteration": 6,
      "phase": "phase2",
      "rmp_objective": 490.283693,
      "artificial_sum": 0.0,
      "route_pool_size": 704,
      "best_reduced_cost": -4.371144,
      "negative_routes": 26,
      "added_routes": 26,
      "exhausted": true,
      "label_pops": 13767,
      "generated_labels": 13764
    },
    {
      "iteration": 7,
      "phase": "phase2",
      "rmp_objective": 490.283693,
      "artificial_sum": 0.0,
      "route_pool_size": 730,
      "best_reduced_cost": -0.0,
      "negative_routes": 0,
      "added_routes": 0,
      "exhausted": true,
      "label_pops": 13767,
      "generated_labels": 13764
    }
  ],
  "fractional_structure": {
    "objective": 490.283693,
    "route_pool_size": 730,
    "support_route_vehicle_variables": 19,
    "fractional_route_vehicle_variables": 19,
    "fractional_y_count": 3,
    "max_task_vehicle_link_violation": 0.0,
    "vehicles": [
      {
        "vehicle": 1,
        "y": 0.553143362,
        "sortie_mass": 2.245212756,
        "sortie_limit_rhs": 9.403437162,
        "work_mass": 132.754407,
        "work_limit_rhs": 132.754407,
        "nonzero_route_count": 7
      },
      {
        "vehicle": 2,
        "y": 0.553143362,
        "sortie_mass": 2.070255835,
        "sortie_limit_rhs": 9.403437162,
        "work_mass": 132.754407,
        "work_limit_rhs": 132.754407,
        "nonzero_route_count": 6
      },
      {
        "vehicle": 3,
        "y": 0.553143362,
        "sortie_mass": 2.184531409,
        "sortie_limit_rhs": 9.403437162,
        "work_mass": 132.754407,
        "work_limit_rhs": 132.754407,
        "nonzero_route_count": 6
      }
    ],
    "top_fractional_routes": [
      {
        "route_id": 23,
        "vehicle": 1,
        "value": 0.5,
        "tasks": [
          13,
          17
        ],
        "cost": 41.227634,
        "load": 5.0,
        "work_time_lb": 50.559613
      },
      {
        "route_id": 434,
        "vehicle": 3,
        "value": 0.553143362,
        "tasks": [
          19,
          10,
          6
        ],
        "cost": 46.54674,
        "load": 5.0,
        "work_time_lb": 56.261051
      },
      {
        "route_id": 19,
        "vehicle": 3,
        "value": 0.553143362,
        "tasks": [
          20
        ],
        "cost": 48.675776,
        "load": 3.0,
        "work_time_lb": 59.5892
      },
      {
        "route_id": 24,
        "vehicle": 2,
        "value": 0.553143362,
        "tasks": [
          5,
          14,
          16,
          12
        ],
        "cost": 53.305861,
        "load": 9.0,
        "work_time_lb": 65.03506
      },
      {
        "route_id": 660,
        "vehicle": 2,
        "value": 0.553143362,
        "tasks": [
          15,
          8,
          4,
          2
        ],
        "cost": 54.287138,
        "load": 9.0,
        "work_time_lb": 68.506232
      },
      {
        "route_id": 24,
        "vehicle": 1,
        "value": 0.446856638,
        "tasks": [
          5,
          14,
          16,
          12
        ],
        "cost": 53.305861,
        "load": 9.0,
        "work_time_lb": 65.03506
      },
      {
        "route_id": 434,
        "vehicle": 1,
        "value": 0.446856638,
        "tasks": [
          19,
          10,
          6
        ],
        "cost": 46.54674,
        "load": 5.0,
        "work_time_lb": 56.261051
      },
      {
        "route_id": 607,
        "vehicle": 2,
        "value": 0.446856638,
        "tasks": [
          17,
          13,
          1
        ],
        "cost": 48.048686,
        "load": 7.0,
        "work_time_lb": 60.444522
      },
      {
        "route_id": 19,
        "vehicle": 1,
        "value": 0.376600802,
        "tasks": [
          20
        ],
        "cost": 48.675776,
        "load": 3.0,
        "work_time_lb": 59.5892
      },
      {
        "route_id": 21,
        "vehicle": 3,
        "value": 0.276571681,
        "tasks": [
          3,
          7,
          18,
          11
        ],
        "cost": 50.594856,
        "load": 7.0,
        "work_time_lb": 62.264476
      },
      {
        "route_id": 226,
        "vehicle": 3,
        "value": 0.276571681,
        "tasks": [
          1,
          9,
          11,
          7,
          3
        ],
        "cost": 50.509755,
        "load": 9.0,
        "work_time_lb": 62.805052
      },
      {
        "route_id": 653,
        "vehicle": 3,
        "value": 0.276571681,
        "tasks": [
          9,
          18
        ],
        "cost": 52.669407,
        "load": 2.0,
        "work_time_lb": 61.669694
      }
    ],
    "top_task_vehicle_splits": [
      {
        "task": 1,
        "vehicle_values": {
          "2": 0.446856638,
          "1": 0.276571681,
          "3": 0.276571681
        },
        "positive_vehicle_count": 3,
        "max_vehicle_value": 0.446856638,
        "entropy": 1.070897825
      },
      {
        "task": 3,
        "vehicle_values": {
          "3": 0.553143362,
          "1": 0.223428319,
          "2": 0.223428319
        },
        "positive_vehicle_count": 3,
        "max_vehicle_value": 0.553143362,
        "entropy": 0.997225482
      },
      {
        "task": 7,
        "vehicle_values": {
          "3": 0.553143362,
          "1": 0.223428319,
          "2": 0.223428319
        },
        "positive_vehicle_count": 3,
        "max_vehicle_value": 0.553143362,
        "entropy": 0.997225482
      },
      {
        "task": 9,
        "vehicle_values": {
          "3": 0.553143362,
          "1": 0.223428319,
          "2": 0.223428319
        },
        "positive_vehicle_count": 3,
        "max_vehicle_value": 0.553143362,
        "entropy": 0.997225482
      },
      {
        "task": 11,
        "vehicle_values": {
          "3": 0.553143362,
          "1": 0.223428319,
          "2": 0.223428319
        },
        "positive_vehicle_count": 3,
        "max_vehicle_value": 0.553143362,
        "entropy": 0.997225482
      },
      {
        "task": 2,
        "vehicle_values": {
          "2": 0.553143362,
          "3": 0.24852964,
          "1": 0.198326997
        },
        "positive_vehicle_count": 3,
        "max_vehicle_value": 0.553143362,
        "entropy": 0.994399481
      },
      {
        "task": 4,
        "vehicle_values": {
          "2": 0.553143362,
          "3": 0.24852964,
          "1": 0.198326997
        },
        "positive_vehicle_count": 3,
        "max_vehicle_value": 0.553143362,
        "entropy": 0.994399481
      },
      {
        "task": 8,
        "vehicle_values": {
          "2": 0.553143362,
          "3": 0.24852964,
          "1": 0.198326997
        },
        "positive_vehicle_count": 3,
        "max_vehicle_value": 0.553143362,
        "entropy": 0.994399481
      },
      {
        "task": 15,
        "vehicle_values": {
          "2": 0.553143362,
          "3": 0.24852964,
          "1": 0.198326997
        },
        "positive_vehicle_count": 3,
        "max_vehicle_value": 0.553143362,
        "entropy": 0.994399481
      },
      {
        "task": 20,
        "vehicle_values": {
          "3": 0.553143362,
          "1": 0.376600802,
          "2": 0.070255835
        },
        "positive_vehicle_count": 3,
        "max_vehicle_value": 0.553143362,
        "entropy": 0.881886343
      },
      {
        "task": 5,
        "vehicle_values": {
          "2": 0.553143362,
          "1": 0.446856638,
          "3": 0
        },
        "positive_vehicle_count": 2,
        "max_vehicle_value": 0.553143362,
        "entropy": 0.687488063
      },
      {
        "task": 6,
        "vehicle_values": {
          "3": 0.553143362,
          "1": 0.446856638,
          "2": 0
        },
        "positive_vehicle_count": 2,
        "max_vehicle_value": 0.553143362,
        "entropy": 0.687488063
      }
    ],
    "fractional_pair_count": 13,
    "top_fractional_pairs": [
      {
        "pair": [
          1,
          3
        ],
        "value": 0.5,
        "fractionality": 0.5
      },
      {
        "pair": [
          1,
          7
        ],
        "value": 0.5,
        "fractionality": 0.5
      },
      {
        "pair": [
          1,
          9
        ],
        "value": 0.5,
        "fractionality": 0.5
      },
      {
        "pair": [
          1,
          11
        ],
        "value": 0.5,
        "fractionality": 0.5
      },
      {
        "pair": [
          1,
          13
        ],
        "value": 0.5,
        "fractionality": 0.5
      },
      {
        "pair": [
          1,
          17
        ],
        "value": 0.5,
        "fractionality": 0.5
      },
      {
        "pair": [
          3,
          9
        ],
        "value": 0.5,
        "fractionality": 0.5
      },
      {
        "pair": [
          3,
          18
        ],
        "value": 0.5,
        "fractionality": 0.5
      },
      {
        "pair": [
          7,
          9
        ],
        "value": 0.5,
        "fractionality": 0.5
      },
      {
        "pair": [
          7,
          18
        ],
        "value": 0.5,
        "fractionality": 0.5
      },
      {
        "pair": [
          9,
          11
        ],
        "value": 0.5,
        "fractionality": 0.5
      },
      {
        "pair": [
          9,
          18
        ],
        "value": 0.5,
        "fractionality": 0.5
      }
    ],
    "fractional_arc_count": 12,
    "top_fractional_arcs": [
      {
        "arc": [
          1,
          9
        ],
        "value": 0.5,
        "fractionality": 0.5
      },
      {
        "arc": [
          3,
          7
        ],
        "value": 0.5,
        "fractionality": 0.5
      },
      {
        "arc": [
          7,
          3
        ],
        "value": 0.5,
        "fractionality": 0.5
      },
      {
        "arc": [
          7,
          18
        ],
        "value": 0.5,
        "fractionality": 0.5
      },
      {
        "arc": [
          9,
          11
        ],
        "value": 0.5,
        "fractionality": 0.5
      },
      {
        "arc": [
          11,
          7
        ],
        "value": 0.5,
        "fractionality": 0.5
      },
      {
        "arc": [
          13,
          1
        ],
        "value": 0.5,
        "fractionality": 0.5
      },
      {
        "arc": [
          13,
          17
        ],
        "value": 0.5,
        "fractionality": 0.5
      },
      {
        "arc": [
          17,
          13
        ],
        "value": 0.5,
        "fractionality": 0.5
      },
      {
        "arc": [
          18,
          11
        ],
        "value": 0.5,
        "fractionality": 0.5
      },
      {
        "arc": [
          9,
          18
        ],
        "value": 0.276571681,
        "fractionality": 0.276571681
      },
      {
        "arc": [
          18,
          9
        ],
        "value": 0.223428319,
        "fractionality": 0.223428319
      }
    ],
    "branch_candidate_counts": {
      "arc": 12,
      "ryan_foster": 13,
      "task_vehicle": 50,
      "vehicle": 3
    }
  },
  "cut_violations": {
    "pair_incompatibility_edges": 70,
    "pair_possible_edges": 190,
    "rci": {
      "violated_count": 0,
      "best_candidate": {
        "tasks": [
          2,
          4,
          8,
          10
        ],
        "size": 4,
        "demand": 10.0,
        "rhs": 4.0,
        "activity": 4.0,
        "violation": 0.0
      },
      "top_violated": []
    },
    "k_path_resource": {
      "stronger_than_capacity_subset_count": 36916,
      "violated_count": 0,
      "best_candidate": {
        "tasks": [
          5,
          15,
          17,
          19,
          20
        ],
        "size": 5,
        "demand": 12.0,
        "capacity_bound": 2,
        "chromatic_bound": 5,
        "k_bound": 5,
        "rhs": 10.0,
        "activity": 10.0,
        "violation": 0.0
      },
      "top_violated": []
    }
  },
  "interpretation": [
    "RCI/RCC 没有起作用的直接原因：当前 root LP 解在枚举范围内没有违反 x(delta(S)) >= 2 ceil(d(S)/Q)。",
    "k-path/resource cut 没有起作用的直接原因：虽然存在资源不兼容 pair，但当前 root LP 解没有违反 x(delta(S)) >= 2 k(S)。",
    "当前 root LP 的主要 fractional 结构集中在任务配对/任务弧选择上，更像 branching 结构问题，而不是容量子集 cut violation。",
    "RMP 根节点仍由多个 fractional route-vehicle column 混合覆盖任务；schedule no-good cut 只在整数 route 集不可排程时触发，不能切这类 fractional 解。",
    "task-vehicle linking 约束在 root LP 中满足，但没有改变 root bound，说明 fixed vehicle cost 稀释不是当前 root bound 的主要瓶颈。"
  ]
}
